infernet_cli/__init__.py
infernet_cli/github.py
infernet_cli/node.py
infernet_cli/recipe.py
infernet_cli/service.py
infernet_cli/cli/__init__.py
infernet_cli/cli/docker.py
infernet_cli/cli/options.py
infernet_cli-1.0.5.dist-info/METADATA
infernet_cli-1.0.5.dist-info/WHEEL
infernet_cli-1.0.5.dist-info/entry_points.txt
infernet_cli-1.0.5.dist-info/RECORD
